eskapade/__init__.py
eskapade/resources.py
eskapade/version.py
eskapade/analysis/__init__.py
eskapade/analysis/correlation.py
eskapade/analysis/datetime.py
eskapade/analysis/histogram.py
eskapade/analysis/histogram_filling.py
eskapade/analysis/statistics.py
eskapade/analysis/links/__init__.py
eskapade/analysis/links/apply_func_to_df.py
eskapade/analysis/links/apply_selection_to_df.py
eskapade/analysis/links/basic_generator.py
eskapade/analysis/links/df_concatenator.py
eskapade/analysis/links/df_merger.py
eskapade/analysis/links/hist_filler.py
eskapade/analysis/links/random_sample_splitter.py
eskapade/analysis/links/read_to_df.py
eskapade/analysis/links/record_factorizer.py
eskapade/analysis/links/record_vectorizer.py
eskapade/analysis/links/value_counter.py
eskapade/analysis/links/write_from_df.py
eskapade/data/LAozone.data.gz
eskapade/data/correlated_data.sv.gz
eskapade/data/dummy.csv
eskapade/data/dummy1.csv
eskapade/data/dummy2.csv
eskapade/data/messy_dtypes.csv
eskapade/data/mock_accounts.csv.gz
eskapade/data_mimic/__init__.py
eskapade/data_mimic/data_mimic_util.py
eskapade/data_mimic/dm_vis_util.py
eskapade/data_mimic/links/__init__.py
eskapade/data_mimic/links/kde_preparation.py
eskapade/data_mimic/links/kernel_density_estimation.py
eskapade/data_mimic/links/mimic_report.py
eskapade/data_mimic/links/mixed_variables_simulation.py
eskapade/data_mimic/links/resample_evaluation.py
eskapade/data_mimic/links/resampler.py
eskapade/data_quality/__init__.py
eskapade/data_quality/dq_helper.py
eskapade/data_quality/links/__init__.py
eskapade/data_quality/links/fix_pandas_dataframe.py
eskapade/logger/__init__.py
eskapade/notebooks/tutorial_1.ipynb
eskapade/templates/__init__.py
eskapade/templates/df_summary_report.tex
eskapade/templates/df_summary_report_page.tex
eskapade/templates/df_summary_table_page.tex
eskapade/tutorials/__init__.py
eskapade/tutorials/esk201_readdata.py
eskapade/tutorials/esk202_writedata.py
eskapade/tutorials/esk203_apply_func_to_pandas_df.py
Eskapade-1.0.0.dist-info/LICENSE
Eskapade-1.0.0.dist-info/METADATA
Eskapade-1.0.0.dist-info/NOTICE
Eskapade-1.0.0.dist-info/WHEEL
Eskapade-1.0.0.dist-info/top_level.txt
Eskapade-1.0.0.dist-info/RECORD
