Metadata-Version: 2.1
Name: Eskapade
Version: 1.0.0
Summary: Eskapade modular analytics
Home-page: http://eskapade.kave.io
Author: KPMG N.V. The Netherlands
Author-email: kave@kpmg.com
License: UNKNOWN
Platform: UNKNOWN
Requires-Python: >=3.6
Requires-Dist: Eskapade-Core (>=1.0.0)
Requires-Dist: matplotlib (>=2.0.2)
Requires-Dist: numpy (>=1.15.0)
Requires-Dist: scipy (>=0.19.0)
Requires-Dist: scikit-learn (>=0.20.1)
Requires-Dist: statsmodels (>=0.8.0)
Requires-Dist: pandas (>=0.20.1)
Requires-Dist: tabulate (>=0.8.2)
Requires-Dist: sortedcontainers (>=1.5.7)
Requires-Dist: histogrammar (>=1.0.9)
Requires-Dist: names (>=0.3.0)
Requires-Dist: fastnumbers (>=2.0.2)
Requires-Dist: phik (>=0.9.3)
Requires-Dist: feather-format (>=0.4.0)
Requires-Dist: pytest (>=3.5.0)
Requires-Dist: pytest-pylint (>=0.9.0)
